ankimaker/__init__.py
ankimaker/cli.py
ankimaker/commands/__init__.py
ankimaker/commands/from_csv.py
ankimaker/commands/from_epub.py
ankimaker/commands/make_config.py
ankimaker/config/__init__.py
ankimaker/config/configuration.py
ankimaker/config/load_config.py
ankimaker/generator/__init__.py
ankimaker/generator/card.py
ankimaker/generator/deck.py
ankimaker/generator/model.py
ankimaker/generator/models.py
ankimaker/tasks/__init__.py
ankimaker/tasks/basic_csv_to_anki.py
ankimaker-0.0.4.dist-info/METADATA
ankimaker-0.0.4.dist-info/WHEEL
ankimaker-0.0.4.dist-info/entry_points.txt
ankimaker-0.0.4.dist-info/top_level.txt
ankimaker-0.0.4.dist-info/RECORD
