Metadata-Version: 2.1
Name: ankimaker
Version: 0.0.4
Summary: Makes anki with files
Home-page: https://git.lgoon.xyz/gabriel/ankimaker
License: BSD-3-Clause
